batch_tr/__init__.py
batch_tr/batch_tr.py
batch_tr-0.1.0.dist-info/WHEEL
batch_tr-0.1.0.dist-info/METADATA
batch_tr-0.1.0.dist-info/RECORD
