Metadata-Version: 2.1
Name: batch-tr
Version: 0.1.0
Summary: batch machine translate via pythonpy
Home-page: https://github.com/ffreemt/batch-tr
License: MIT
Author: freemt
Requires-Python: >=3.6.7,<4.0.0
Classifier: License :: OSI Approved :: MIT License
Classifier: Programming Language :: Python :: 3
Classifier: Programming Language :: Python :: 3.7
Classifier: Programming Language :: Python :: 3.8
Classifier: Programming Language :: Python :: 3.9
Requires-Dist: logzero (>=1.7.0,<2.0.0)
Requires-Dist: translatepy (>=1.7,<2.0)
Project-URL: Repository, https://github.com/ffreemt/batch-tr
